torch_directml_native.cp311-win_amd64.pyd
torch_directml/DirectML.dll
torch_directml/__init__.py
torch_directml/device.py
torch_directml/functions.py
torch_directml/csrc/auto_gen_yaml.py
torch_directml-0.2.5.dev240914.dist-info/LICENSE
torch_directml-0.2.5.dev240914.dist-info/METADATA
torch_directml-0.2.5.dev240914.dist-info/NOTICE
torch_directml-0.2.5.dev240914.dist-info/WHEEL
torch_directml-0.2.5.dev240914.dist-info/top_level.txt
torch_directml-0.2.5.dev240914.dist-info/RECORD
